nyancad_server/__init__.py
nyancad_server/config.py
nyancad_server/mcp_server.py
nyancad_server/notebook.py
nyancad_server/notebook_middleware.py
nyancad_server/oauth.py
nyancad_server/server.py
nyancad_server/public/design-doc.json
nyancad_server/public/index.html
nyancad_server/public/auth/index.html
nyancad_server/public/css/style.css
nyancad_server/public/css/icons/Logo.svg
nyancad_server/public/css/icons/arrows-move.svg
nyancad_server/public/css/icons/eraser.svg
nyancad_server/public/css/icons/pencil.svg
nyancad_server/public/css/icons/search.svg
nyancad_server/public/docs/Annotations.html
nyancad_server/public/docs/Architecture.html
nyancad_server/public/docs/Deployment.html
nyancad_server/public/docs/Documentation.html
nyancad_server/public/docs/Editor-overview.html
nyancad_server/public/docs/Getting-started-instructions.html
nyancad_server/public/docs/Keyboard-shortcuts.html
nyancad_server/public/docs/Library-Manager-Overview.html
nyancad_server/public/docs/MCP-Server.html
nyancad_server/public/docs/Mosaic-design:-Personas.html
nyancad_server/public/docs/Mosaic-design:-Requirements.html
nyancad_server/public/docs/PDK-management.html
nyancad_server/public/docs/Python-API.html
nyancad_server/public/docs/Simulator-overview.html
nyancad_server/public/docs/Video-tutorials.html
nyancad_server/public/docs/edalogo.png
nyancad_server/public/docs/edalogo.svg
nyancad_server/public/docs/index.html
nyancad_server/public/docs/jupyter.gif
nyancad_server/public/docs/mosaic.gif
nyancad_server/public/docs/mosaic.png
nyancad_server/public/docs/mosaic.svg
nyancad_server/public/docs/assets/css/style.css
nyancad_server/public/docs/assets/css/style.css.map
nyancad_server/public/docs/assets/images/Mosiac Logo.png
nyancad_server/public/docs/assets/images/arrow-up-right-square.png
nyancad_server/public/docs/assets/images/bg_hr.png
nyancad_server/public/docs/assets/images/blacktocat.png
nyancad_server/public/docs/assets/images/book.png
nyancad_server-0.12.6.dist-info/METADATA
nyancad_server-0.12.6.dist-info/WHEEL
nyancad_server-0.12.6.dist-info/entry_points.txt
nyancad_server-0.12.6.dist-info/top_level.txt
nyancad_server-0.12.6.dist-info/RECORD
