Metadata-Version: 2.4
Name: nyancad-server
Version: 0.12.6
Summary: NyanCAD server package with marimo integration
Author-email: Pepijn de Vos <me@pepijndevos.nl>
License: MPL-2.0
Project-URL: Homepage, https://github.com/NyanCAD/Mosaic
Project-URL: Repository, https://github.com/NyanCAD/Mosaic
Classifier: Development Status :: 3 - Alpha
Classifier: Intended Audience :: Developers
Classifier: License :: OSI Approved :: Mozilla Public License 2.0 (MPL 2.0)
Classifier: Programming Language :: Python :: 3
Classifier: Programming Language :: Python :: 3.8
Classifier: Programming Language :: Python :: 3.9
Classifier: Programming Language :: Python :: 3.10
Classifier: Programming Language :: Python :: 3.11
Classifier: Programming Language :: Python :: 3.12
Requires-Python: >=3.8
Requires-Dist: marimo>=0.15.0
Requires-Dist: uvicorn[standard]>=0.23.0
Requires-Dist: nyancad>=0.10.2
Requires-Dist: httpx>=0.25.0
Requires-Dist: slowapi>=0.1.9
Requires-Dist: mcp>=1.0.0
Requires-Dist: pyjwt[crypto]>=2.10.1
